kapipe/__init__.py
kapipe/utils.py
kapipe/chunking/__init__.py
kapipe/chunking/chunker.py
kapipe/community_clustering/__init__.py
kapipe/community_clustering/hierarchical_leiden.py
kapipe/community_clustering/neighborhood_aggregation.py
kapipe/community_clustering/triple_level_factorization.py
kapipe/datatypes/__init__.py
kapipe/datatypes/datatypes.py
kapipe/demonstration_retrieval/__init__.py
kapipe/demonstration_retrieval/demonstration_retriever.py
kapipe/docre/__init__.py
kapipe/docre/atlop.py
kapipe/docre/docre.py
kapipe/docre/llm_docre.py
kapipe/docre/ma_atlop.py
kapipe/docre/ma_qa.py
kapipe/ed_reranking/__init__.py
kapipe/ed_reranking/blink_cross_encoder.py
kapipe/ed_reranking/ed_reranking.py
kapipe/ed_reranking/identical_entity_reranker.py
kapipe/ed_reranking/llm_ed.py
kapipe/ed_retrieval/__init__.py
kapipe/ed_retrieval/blink_bi_encoder.py
kapipe/ed_retrieval/dummy_entity_retriever.py
kapipe/ed_retrieval/ed_retrieval.py
kapipe/ed_retrieval/lexical_entity_retriever.py
kapipe/evaluation/__init__.py
kapipe/evaluation/docre/__init__.py
kapipe/evaluation/docre/docred_official.py
kapipe/evaluation/docre/fscore.py
kapipe/evaluation/ed/__init__.py
kapipe/evaluation/ed/accuracy.py
kapipe/evaluation/ed/entity_level_fscore.py
kapipe/evaluation/ed/fscore.py
kapipe/evaluation/ed/recall_at_k.py
kapipe/evaluation/ner/__init__.py
kapipe/evaluation/ner/fscore.py
kapipe/evaluation/passage_retrieval/__init__.py
kapipe/evaluation/passage_retrieval/mean_average_precision.py
kapipe/evaluation/passage_retrieval/mean_reciprocal_rank.py
kapipe/evaluation/passage_retrieval/ndcg_at_k.py
kapipe/evaluation/passage_retrieval/precision_recall_at_k.py
kapipe/evaluation/qa/__init__.py
kapipe/evaluation/qa/accuracy.py
kapipe/evaluation/qa/llm4eval.py
kapipe/evaluation/qa/recall.py
kapipe/knowledge_graph_construction/__init__.py
kapipe/knowledge_graph_construction/knowledge_graph_constructor.py
kapipe/knowledge_graph_construction/knowledge_graph_visualization.py
kapipe/llms/__init__.py
kapipe-0.1.2.dist-info/licenses/LICENSE
kapipe-0.1.2.dist-info/METADATA
kapipe-0.1.2.dist-info/WHEEL
kapipe-0.1.2.dist-info/top_level.txt
kapipe-0.1.2.dist-info/RECORD
