Metadata-Version: 2.4
Name: kapipe
Version: 0.1.2
Summary: A modular pipeline for knowledge acquisition
Author-email: Noriki Nishida <norikinishida@gmail.com>
License: LICENSE
Project-URL: Homepage, https://github.com/norikinishida/kapipe
Keywords: NLP,knowledge acquisition,information extraction,knowledge graph,retrieval,question answering
Platform: UNKNOWN
Classifier: Development Status :: 4 - Beta
Classifier: Intended Audience :: Developers
Classifier: Intended Audience :: Science/Research
Classifier: License :: OSI Approved :: Apache Software License
Classifier: Operating System :: OS Independent
Classifier: Programming Language :: Python :: 3.10
Classifier: Topic :: Scientific/Engineering :: Artificial Intelligence
Requires-Python: >=3.10
License-File: LICENSE
Requires-Dist: numpy>=1.22.2
Requires-Dist: scipy>=1.10.1
Requires-Dist: pandas>=1.5.3
Requires-Dist: spacy>=3.7.1
Requires-Dist: spacy-alignments>=0.9.1
Requires-Dist: scispacy
Requires-Dist: torch>=2.6.0
Requires-Dist: torch-tensorrt
Requires-Dist: torchdata
Requires-Dist: torchtext
Requires-Dist: torchvision
Requires-Dist: opt-einsum>=3.3.0
Requires-Dist: transformers>=4.46.0
Requires-Dist: accelerate>=1.0.1
Requires-Dist: bitsandbytes>=0.44.1
Requires-Dist: openai>=1.53.0
Requires-Dist: tenacity>=9.1.2
Requires-Dist: faiss-gpu-cu12>=1.12.0
Requires-Dist: Levenshtein>=0.25.0
Requires-Dist: networkx>=3.4.2
Requires-Dist: neo4j>=5.25.0
Requires-Dist: graspologic>=3.4.1
Requires-Dist: future>=1.0.0
Requires-Dist: pyhocon>=0.3.60
Requires-Dist: tqdm>=4.66.1
Requires-Dist: jsonlines>=4.0.0
Dynamic: license-file
